setup.py
SafeHaven_Python_SDK.egg-info/PKG-INFO
SafeHaven_Python_SDK.egg-info/SOURCES.txt
SafeHaven_Python_SDK.egg-info/dependency_links.txt
SafeHaven_Python_SDK.egg-info/requires.txt
SafeHaven_Python_SDK.egg-info/top_level.txt
SafeHaven_Python_SDK.egg-info/zip-safe
dgpy/__init__.py
dgpy/cms_client.py
dgpy/conf_file.py
dgpy/dvol.py
dgpy/errors.py
dgpy/interceptor.py
dgpy/job.py
dgpy/user.py
dgpy/utils.py
dgpy/version.py
dgpy/aggregates/__init__.py
dgpy/aggregates/cluster/__init__.py
dgpy/aggregates/cluster/cluster_pb2.py
dgpy/aggregates/cluster/cluster_pb2_grpc.py
dgpy/aggregates/disk/__init__.py
dgpy/aggregates/disk/disk_pb2.py
dgpy/aggregates/disk/disk_pb2_grpc.py
dgpy/aggregates/dvol/__init__.py
dgpy/aggregates/dvol/dvol_enums_pb2.py
dgpy/aggregates/dvol/dvol_enums_pb2_grpc.py
dgpy/aggregates/dvol/dvol_pb2.py
dgpy/aggregates/dvol/dvol_pb2_grpc.py
dgpy/aggregates/dvol/pg/__init__.py
dgpy/aggregates/dvol/pg/pg_enums_pb2.py
dgpy/aggregates/dvol/pg/pg_enums_pb2_grpc.py
dgpy/aggregates/dvol/target/__init__.py
dgpy/aggregates/dvol/target/target_enums_pb2.py
dgpy/aggregates/dvol/target/target_enums_pb2_grpc.py
dgpy/aggregates/site/__init__.py
dgpy/aggregates/site/site_pb2.py
dgpy/aggregates/site/site_pb2_grpc.py
dgpy/magicbus/__init__.py
dgpy/magicbus/command/__init__.py
dgpy/magicbus/command/command_enums_pb2.py
dgpy/magicbus/command/command_enums_pb2_grpc.py
dgpy/messaging/__init__.py
dgpy/messaging/dgcomm/__init__.py
dgpy/messaging/dgcomm/message/__init__.py
dgpy/messaging/dgcomm/message/protocol_number.py
dgpy/messaging/dgcomm/message/syntropy_message_pb2.py
dgpy/messaging/dgcomm/message/syntropy_message_pb2_grpc.py
dgpy/messaging/shcomm/__init__.py
dgpy/messaging/shcomm/peer/__init__.py
dgpy/messaging/shcomm/peer/peer_enums_pb2.py
dgpy/messaging/shcomm/peer/peer_enums_pb2_grpc.py
dgpy/safehaven/__init__.py
dgpy/safehaven/api/__init__.py
dgpy/safehaven/api/api_pb2.py
dgpy/safehaven/api/api_pb2_grpc.py
dgpy/safehaven/api/types/__init__.py
dgpy/safehaven/api/types/types_enums_pb2.py
dgpy/safehaven/api/types/types_enums_pb2_grpc.py
dgpy/safehaven/cron/__init__.py
dgpy/safehaven/cron/cron_pb2.py
dgpy/safehaven/cron/cron_pb2_grpc.py
dgpy/safehaven/jobsystem/__init__.py
dgpy/safehaven/jobsystem/jobsystem_pb2.py
